pdfsmartocr/__init__.py
pdfsmartocr/ocr.py
pdfsmartocr-0.1.4.dist-info/LICENSE
pdfsmartocr-0.1.4.dist-info/METADATA
pdfsmartocr-0.1.4.dist-info/WHEEL
pdfsmartocr-0.1.4.dist-info/top_level.txt
pdfsmartocr-0.1.4.dist-info/RECORD
