Metadata-Version: 2.2
Name: pdfsmartocr
Version: 0.1.4
Summary: OCR híbrido: Tesseract + PdfReader com paralelismo automático para PDFs grandes.
Author-email: Rafael Galvão <seuemail@example.com>
License: MIT
Classifier: Development Status :: 4 - Beta
Classifier: Intended Audience :: Developers
Classifier: Intended Audience :: Legal Industry
Classifier: License :: OSI Approved :: MIT License
Classifier: Operating System :: OS Independent
Classifier: Programming Language :: Python :: 3
Classifier: Topic :: Text Processing
Classifier: Topic :: Utilities
Requires-Python: >=3.8
License-File: LICENSE
Requires-Dist: pytesseract
Requires-Dist: pdf2image
Requires-Dist: PyPDF2
Requires-Dist: Pillow
